genius_core_client-0.4.0.dist-info/METADATA
genius_core_client-0.4.0.dist-info/WHEEL
genius_core_client/__init__.py
genius_core_client/genius_core_client.cpython-312-aarch64-linux-gnu.so
genius_core_client-0.4.0.dist-info/RECORD
