Metadata-Version: 2.3
Name: genius-core-client
Version: 0.4.0
Summary: Genius Core Client Library. Written in Rust and using PyO3 for Python bindings.
License: Apache-2.0
